scr/ganna_v1/__init__.py
scr/ganna_v1/ganna.py
scr/ganna_v1/.ipynb_checkpoints/Untitled-checkpoint.ipynb
scr/ganna_v1/.ipynb_checkpoints/Untitled1-checkpoint.ipynb
scr/ganna_v1/.ipynb_checkpoints/gen_str-checkpoint.py
ganna_v1-0.0.3.dist-info/METADATA
ganna_v1-0.0.3.dist-info/WHEEL
ganna_v1-0.0.3.dist-info/licenses/LICENSE
ganna_v1-0.0.3.dist-info/RECORD
