Metadata-Version: 2.1
Name: ganna_v1
Version: 0.0.3
Summary: Generative Algorithm for N-Doped Novel Aromatics
Author-email: Stiv Llenga <stiv.llenga@h-its.org>
License-File: LICENSE
Classifier: License :: OSI Approved :: MIT License
Classifier: Operating System :: OS Independent
Classifier: Programming Language :: Python :: 3
Requires-Python: >=3.7
